{
    "greeting": ["สวัสดีค่า หนูชื่อมีนาา\n\nสงสัยป่าว ว่ามีนาแล้ว เมื่อไหร่จะมีแฟน เอ้ย!\nมีคลีนรูม แฮร่", "สวัสดีค่าาา"],
    "objective":["ช่วงนี้อากาศฝุ่นควันเยอะ เรามาช่วยแบ่งปันข้อมูลพื้นที่ปลอดภัยให้กับเพื่อนๆ รอบตัวกันนะคะ"],
    "get_image": ["ขอภาพ clean room หรือห้องที่มีเครื่องฟอกอากาศหน่อยน้าาา \nเพื่อนๆ คนอื่นจะได้หาเจอ"],
    "get_location": ["ส่งโลเคชันให้เค้าหน่อยน้าาาา"],
    "get_name": ["ขอชื่อสถานที่หน่อยน้าาา พิมพ์มาบอกเค้าได้เลย\n(พิมพ์คำว่าร้าน/ห้อง/อาคาร... ด้วยน้าาา)"],
    "get_category": ["เป็นสถานที่ประเภทไหนอ่า"],
    "thankyou": ["ขอบคุณน้าาาา"],
    "end":["ขอบคุณน้าา ถ้าเจอคลีนรูมเพิ่ม\nอย่าลืมมาบอกมีนา น้าาาาา"]
}

